aoi/__init__.py
aoi/__main__.py
aoi/_misc.py
aoi/base.py
aoi/sqlite.py
aoi-0.1.1.dist-info/METADATA
aoi-0.1.1.dist-info/WHEEL
aoi-0.1.1.dist-info/RECORD
