Metadata-Version: 2.1
Name: aoi
Version: 0.1.1
Summary: SQLITE3 CLI wrapper build on python.
License: MIT
Author: sarthhh
Author-email: shiva02939@gmail.com
Requires-Python: >=3.8,<4.0
Classifier: License :: OSI Approved :: MIT License
Classifier: Programming Language :: Python :: 3
Classifier: Programming Language :: Python :: 3.8
Classifier: Programming Language :: Python :: 3.9
Classifier: Programming Language :: Python :: 3.10
Classifier: Programming Language :: Python :: 3.11
Requires-Dist: colorama (>=0.4.6,<0.5.0)
